classomfier/__init__.py
classomfier/bin/__init__.py
classomfier/bin/classomfier.f90
classomfier/bin/nomatrix.f90
classomfier/test/__init__.py
classomfier-0.2.dist-info/LICENSE
classomfier-0.2.dist-info/METADATA
classomfier-0.2.dist-info/WHEEL
classomfier-0.2.dist-info/top_level.txt
classomfier-0.2.dist-info/RECORD
