Metadata-Version: 2.1
Name: classomfier
Version: 0.2
Summary: ClasSOMfier: A neural network for cluster analysis and detection of lattice defects
Home-page: https://github.com/JaviFdezT/ClasSOMfier
Author: Javier F. Troncoso
Author-email: javierfdeztroncoso@gmail.com
License: LICENSE.txt
Download-URL: https://github.com/JaviFdezT/ClasSOMfier/archive/0.2.tar.gz
Keywords: kohonen,neural,network,cluster,analysis
Platform: UNKNOWN
